README.md
setup.py
sphinx_csharp/__init__.py
sphinx_csharp/csharp.py
sphinx_csharp.egg-info/PKG-INFO
sphinx_csharp.egg-info/SOURCES.txt
sphinx_csharp.egg-info/dependency_links.txt
sphinx_csharp.egg-info/requires.txt
sphinx_csharp.egg-info/top_level.txt