Metadata-Version: 1.1
Name: sphinx-csharp
Version: 0.1.6
Summary: C# domain for Sphinx
Home-page: https://github.com/djungelorm/sphinx-csharp
Author: djungelorm
Author-email: djungelorm@users.noreply.github.com
License: MIT
Platform: UNKNOWN
Classifier: Development Status :: 4 - Beta
Classifier: Intended Audience :: Developers
Classifier: License :: OSI Approved :: MIT License
Classifier: Natural Language :: English
Classifier: Programming Language :: Python :: 2.6
Classifier: Programming Language :: Python :: 2.7
Classifier: Programming Language :: Python :: 3.3
Classifier: Programming Language :: Python :: 3.4
Classifier: Programming Language :: Python :: 3.5
Classifier: Operating System :: OS Independent
Classifier: Topic :: Documentation :: Sphinx
